__init__.py
lsdyna_parser/__init__.py
lsdyna_parser/lsdyna_parser.py
lsdyna_parser-0.0.1.dist-info/LICENSE
lsdyna_parser-0.0.1.dist-info/METADATA
lsdyna_parser-0.0.1.dist-info/WHEEL
lsdyna_parser-0.0.1.dist-info/top_level.txt
lsdyna_parser-0.0.1.dist-info/RECORD
