Metadata-Version: 2.1
Name: lsdyna-parser
Version: 0.0.1
Summary: Simple parser for LS-Dyna decks
Author-email: Marwin Budniok <marwin.budniok@aol.com>
Project-URL: Homepage, https://github.com/marwin-budniok/lsdyna_parser
Classifier: Programming Language :: Python :: 3
Classifier: License :: OSI Approved :: MIT License
Classifier: Operating System :: OS Independent
Requires-Python: >=3.7
License-File: LICENSE
